MANIFEST.in
README.md
requirements.txt
setup.py
dj_analytics.egg-info/PKG-INFO
dj_analytics.egg-info/SOURCES.txt
dj_analytics.egg-info/dependency_links.txt
dj_analytics.egg-info/not-zip-safe
dj_analytics.egg-info/requires.txt
dj_analytics.egg-info/top_level.txt
djanalytics/__init__.py
djanalytics/encoders.py
djanalytics/http.py
djanalytics/middleware.py
djanalytics/models.py
djanalytics/urls.py
djanalytics/views.py
djanalytics/admin/__init__.py
djanalytics/admin/client.py
djanalytics/admin/reports.py
djanalytics/charts/__init__.py
djanalytics/charts/forms.py
djanalytics/charts/urls.py
djanalytics/charts/views/__init__.py
djanalytics/charts/views/base.py
djanalytics/charts/views/exit_page.py
djanalytics/charts/views/page_visit.py
djanalytics/charts/views/referrer.py
djanalytics/charts/views/session.py
djanalytics/charts/views/user.py
djanalytics/django_migrations/0001_initial.py
djanalytics/django_migrations/0002_prepopulate_types.py
djanalytics/django_migrations/0003_auto_20151120_1755.py
djanalytics/django_migrations/__init__.py
djanalytics/management/__init__.py
djanalytics/management/commands/__init__.py
djanalytics/management/commands/collect_reporting_stats.py
djanalytics/migrations/0001_initial.py
djanalytics/migrations/0002_auto__add_field_requestevent_referrer__add_index_requestevent_domain__.py
djanalytics/migrations/0003_auto__add_location__add_field_requestevent_location.py
djanalytics/migrations/0004_auto__chg_field_requestevent_created.py
djanalytics/migrations/0005_auto__chg_field_requestevent_referrer.py
djanalytics/migrations/0006_auto__add_field_requestevent_screen_width__add_field_requestevent_scre.py
djanalytics/migrations/0007_auto__add_device__add_webproperty__add_pagevisit__add_visitor__add_pag.py
djanalytics/migrations/0008_prepopulate_types.py
djanalytics/migrations/0009_auto__add_field_device_user_agent_md5__add_index_device_screen_width__.py
djanalytics/migrations/0010_auto__chg_field_requestevent_ip_address.py
djanalytics/migrations/__init__.py
djanalytics/reports/__init__.py
djanalytics/reports/forms.py
djanalytics/reports/models.py
djanalytics/reports/urls.py
djanalytics/reports/utils.py
djanalytics/reports/validators.py
