Metadata-Version: 1.1
Name: dj-analytics
Version: 1.0.6
Summary: Django app to capture, track and display site analytics
Home-page: https://github.com/analytehealth/django-analytics
Author: Analyte Health
Author-email: tech@analytehealth.com
License: UNKNOWN
Download-URL: https://github.com/analytehealth/django-analytics/archive/1.0.6.tar.gz
Platform: UNKNOWN
